LICENSE
MANIFEST.in
README.rst
pyproject.toml
setup.py
django_sitewide.egg-info/PKG-INFO
django_sitewide.egg-info/SOURCES.txt
django_sitewide.egg-info/dependency_links.txt
django_sitewide.egg-info/requires.txt
django_sitewide.egg-info/top_level.txt
sitewide/__init__.py
sitewide/admin.py
sitewide/apps.py
sitewide/models.py
sitewide/tests.py
sitewide/urls.py
sitewide/views.py
sitewide/docs/conf.py
sitewide/docs/_build/doctrees/environment.pickle
sitewide/docs/_build/doctrees/explanations.doctree
sitewide/docs/_build/doctrees/how-tos.doctree
sitewide/docs/_build/doctrees/index.doctree
sitewide/docs/_build/doctrees/references.doctree
sitewide/docs/_build/doctrees/tutorials.doctree
sitewide/docs/_build/html/.buildinfo
sitewide/docs/_build/html/explanations.html
sitewide/docs/_build/html/genindex.html
sitewide/docs/_build/html/how-tos.html
sitewide/docs/_build/html/index.html
sitewide/docs/_build/html/objects.inv
sitewide/docs/_build/html/references.html
sitewide/docs/_build/html/search.html
sitewide/docs/_build/html/searchindex.js
sitewide/docs/_build/html/tutorials.html
sitewide/docs/_build/html/_sources/explanations.rst.txt
sitewide/docs/_build/html/_sources/how-tos.rst.txt
sitewide/docs/_build/html/_sources/index.rst.txt
sitewide/docs/_build/html/_sources/references.rst.txt
sitewide/docs/_build/html/_sources/tutorials.rst.txt
sitewide/docs/_build/html/_static/0fecf1cc5677455886b4.woff2
sitewide/docs/_build/html/_static/1d5fc702ab9000c3247a.woff
sitewide/docs/_build/html/_static/2fe080a3bf49bdc12fcb.woff2
sitewide/docs/_build/html/_static/39bd78ffb50669d6855a.woff
sitewide/docs/_build/html/_static/4f183a25813446a47ad9.woff2
sitewide/docs/_build/html/_static/5f68b8c26e28d783a591.woff2
sitewide/docs/_build/html/_static/63a0f5d460fb58135365.woff
sitewide/docs/_build/html/_static/70e1dc5f5622381d6e9e.woff
sitewide/docs/_build/html/_static/84504970850f0632d9c3.woff
sitewide/docs/_build/html/_static/a1e4997bd1fb9d7822e1.woff2
sitewide/docs/_build/html/_static/a61d04152f1635036f0d.woff2
sitewide/docs/_build/html/_static/alabaster.css
sitewide/docs/_build/html/_static/awesome-docsearch.css
sitewide/docs/_build/html/_static/awesome-docsearch.js
