Metadata-Version: 2.4
Name: django-sitewide
Version: 0.1.51
Summary: A Django App for creating and maintaining consistent looks across a django website.
Author-email: Onyeibo Oku <onyeibo@schemefusion.com>
Maintainer-email: Onyeibo Oku <onyeibo@schemefusion.com>
License-Expression: GPL-3.0-or-later
Project-URL: Homepage, https://gitlab.com/twohot/django-sitewide
Project-URL: Documentation, https://gitlab.com/twohot/django-sitewide
Project-URL: Repository, https://gitlab.com/twohot/django-sitewide
Project-URL: Bug Tracker, https://gitlab.com/twohot/django-sitewide
Project-URL: Changelog, https://gitlab.com/twohot/django-sitewide
Keywords: site,sitewide,consistent,theme
Classifier: Environment :: Web Environment
Classifier: Framework :: Django :: 5.1
Classifier: Intended Audience :: Developers
Classifier: Operating System :: OS Independent
Classifier: Programming Language :: Python :: 3.13
Requires-Python: >=3.12
License-File: LICENSE
Requires-Dist: django
Requires-Dist: pyyaml
Dynamic: license-file
